distributed_pg_lock/__init__.py
distributed_pg_lock/db.py
distributed_pg_lock/distributed_lock.py
distributed_pg_lock/exceptions.py
distributed_pg_lock/models.py
distributed_pg_lock-0.1.2.dist-info/licenses/LICENSE
distributed_pg_lock-0.1.2.dist-info/METADATA
distributed_pg_lock-0.1.2.dist-info/WHEEL
distributed_pg_lock-0.1.2.dist-info/top_level.txt
distributed_pg_lock-0.1.2.dist-info/RECORD
