Metadata-Version: 2.4
Name: distributed-pg-lock
Version: 0.1.2
Summary: A robust distributed locking system using PostgreSQL for coordinating resource access across distributed systems with automatic heartbeating, timeout management, and stale lock recovery.
Home-page: https://github.com/surendrahingane/distributed-pg-lock
Author: Surendra Sahadeo Hingane
Author-email: surendrahingne@gmail.com
Classifier: Programming Language :: Python :: 3
Classifier: License :: OSI Approved :: MIT License
Classifier: Operating System :: OS Independent
Requires-Python: >=3.8
License-File: LICENSE
Requires-Dist: sqlalchemy>=1.4
Requires-Dist: tenacity>=8.0
Provides-Extra: test
Requires-Dist: pytest; extra == "test"
Requires-Dist: psycopg2-binary; extra == "test"
Dynamic: classifier
Dynamic: license-file
Dynamic: provides-extra
Dynamic: requires-dist
